logger_extras/__init__.py
logger_extras/_version.py
logger_extras/filters.py
logger_extras/formatters.py
logger_extras/mqtt.py
logger_extras/py.typed
logger_extras/utils.py
logger_extras-0.4.1.dist-info/LICENSE
logger_extras-0.4.1.dist-info/METADATA
logger_extras-0.4.1.dist-info/WHEEL
logger_extras-0.4.1.dist-info/top_level.txt
logger_extras-0.4.1.dist-info/RECORD
