Metadata-Version: 2.1
Name: logger_extras
Version: 0.4.1
Summary: A collection of useful logging tools
Author: Will Barber
License: MIT License
Project-URL: Repository, https://github.com/WillB97/logger-extras
Project-URL: Homepage, https://github.com/WillB97/logger-extras
Classifier: Topic :: Software Development :: Libraries :: Python Modules
Classifier: Programming Language :: Python :: 3
Classifier: Operating System :: OS Independent
Classifier: Development Status :: 4 - Beta
Classifier: Typing :: Typed
Requires-Python: >=3.8
License-File: LICENSE
Requires-Dist: typing-extensions ; python_version < "3.10"
Provides-Extra: dev
Requires-Dist: poethepoet <1,>=0.0.1 ; extra == 'dev'
Requires-Dist: ruff <0.4,>=0.3.0 ; extra == 'dev'
Requires-Dist: mypy ==1.9.0 ; extra == 'dev'
Requires-Dist: build ; extra == 'dev'
Requires-Dist: pytest ; extra == 'dev'
Requires-Dist: pytest-cov ; extra == 'dev'
Requires-Dist: paho-mqtt <3,>=2 ; extra == 'dev'
Provides-Extra: mqtt
Requires-Dist: paho-mqtt <3,>=2 ; extra == 'mqtt'
